awslogs/__init__.py
awslogs/__main__.py
awslogs/_version.py
awslogs/bin.py
awslogs/core.py
awslogs/exceptions.py
awslogs-0.15.0.dist-info/AUTHORS
awslogs-0.15.0.dist-info/COPYING
awslogs-0.15.0.dist-info/METADATA
awslogs-0.15.0.dist-info/WHEEL
awslogs-0.15.0.dist-info/entry_points.txt
awslogs-0.15.0.dist-info/top_level.txt
awslogs-0.15.0.dist-info/RECORD
